pymilvus/__init__.py
pymilvus/decorators.py
pymilvus/settings.py
pymilvus/client/__init__.py
pymilvus/client/abstract.py
pymilvus/client/asynch.py
pymilvus/client/blob.py
pymilvus/client/check.py
pymilvus/client/configs.py
pymilvus/client/constants.py
pymilvus/client/exceptions.py
pymilvus/client/grpc_handler.py
pymilvus/client/prepare.py
pymilvus/client/singleton_utils.py
pymilvus/client/stub.py
pymilvus/client/ts_utils.py
pymilvus/client/types.py
pymilvus/client/utils.py
pymilvus/grpc_gen/__init__.py
pymilvus/grpc_gen/common_pb2.py
pymilvus/grpc_gen/milvus_pb2.py
pymilvus/grpc_gen/milvus_pb2_grpc.py
pymilvus/grpc_gen/schema_pb2.py
pymilvus/grpc_gen/proto/common.proto
pymilvus/grpc_gen/proto/milvus.proto
pymilvus/grpc_gen/proto/python_gen.sh
pymilvus/grpc_gen/proto/schema.proto
pymilvus/orm/__init__.py
pymilvus/orm/collection.py
pymilvus/orm/connections.py
pymilvus/orm/constants.py
pymilvus/orm/default_config.py
pymilvus/orm/exceptions.py
pymilvus/orm/future.py
pymilvus/orm/index.py
pymilvus/orm/mutation.py
pymilvus/orm/partition.py
pymilvus/orm/prepare.py
pymilvus/orm/schema.py
pymilvus/orm/search.py
pymilvus/orm/types.py
pymilvus/orm/utility.py
pymilvus_legacy-2.0.2.post0.dist-info/LICENSE
pymilvus_legacy-2.0.2.post0.dist-info/METADATA
pymilvus_legacy-2.0.2.post0.dist-info/WHEEL
pymilvus_legacy-2.0.2.post0.dist-info/top_level.txt
pymilvus_legacy-2.0.2.post0.dist-info/RECORD
