Metadata-Version: 2.1
Name: pymilvus-legacy
Version: 2.0.2.post0
Summary: Python Sdk for Milvus
Home-page: https://github.com/milvus-io/pymilvus
Author: Milvus Team
Author-email: milvus-team@zilliz.com
License: Apache-2.0
Platform: UNKNOWN
Classifier: Programming Language :: Python :: 3.6
Classifier: Programming Language :: Python :: 3.7
Classifier: Programming Language :: Python :: 3.8
Requires-Python: >=3.6
License-File: LICENSE
Requires-Dist: grpcio (==1.37.1)
Requires-Dist: grpcio-tools (==1.37.1)
Requires-Dist: ujson (<=5.1.0,>=1.35)
Requires-Dist: mmh3 (<=3.0.0,>=2.0)
Requires-Dist: pandas (==1.1.5) ; python_version < "3.7"
Requires-Dist: pandas (>=1.2.4) ; python_version > "3.6"
